examples/01_blink_led/rtl/top.v
// Golden Example 01: Blink LED
module top (
    input wire clk,
    output reg led
);
    reg [23:0] counter = 24'd0;

    always @(posedge clk) begin
        counter <= counter + 1'b1;
        if (counter == 24'd12_000_000) begin
            counter <= 24'd0;
            led <= ~led;
        end
    end
endmodule

examples/01_blink_led/sim/tb_top.v
`timescale 1ns/1ps
module tb_top;
    reg clk = 0;
    wire led;

    top uut (
        .clk(clk),
        .led(led)
    );

    always #5 clk = ~clk;

    initial begin
        $dumpfile("build/waveform.vcd");
        $dumpvars(0, tb_top);
        #500;
        $finish;
    end
endmodule

examples/01_blink_led/build/waveform.vcd
$date
	Tue Sep 15 22:47:02 2026
$end
$version
	Icarus Verilog
$end
$timescale
	1ps
$end
$scope module tb_top $end
$var wire 1 ! led $end
$var reg 1 " clk $end
$scope module uut $end
$var wire 1 " clk $end
$var reg 24 # counter [23:0] $end
$var reg 1 ! led $end
$upscope $end
$upscope $end
$enddefinitions $end
$comment Show the parameter values. $end
$dumpall
$end
#0
$dumpvars
b0 #
0"
x!
$end
#5000
b1 #
1"
#10000
0"
#15000
b10 #
1"
#20000
0"
#25000
b11 #
1"
#30000
0"
#35000
b100 #
1"
#40000
0"
#45000
b101 #
1"
#50000
0"
#55000
b110 #
1"
#60000
0"
#65000
b111 #
1"
#70000
0"
#75000
b1000 #
1"
#80000
0"
#85000
b1001 #
1"
#90000
0"
#95000
b1010 #
1"
#100000
0"
#105000
b1011 #
1"
#110000
0"
#115000
b1100 #
1"
#120000
0"
#125000
b1101 #
1"
#130000
0"
#135000
b1110 #
1"
#140000
0"
#145000
b1111 #
1"
#150000
0"
#155000
b10000 #
1"
#160000
0"
#165000
b10001 #
1"
#170000
0"
#175000
b10010 #
1"
#180000
0"
#185000
b10011 #
1"
#190000
0"
#195000
b10100 #
1"
#200000
0"
#205000
b10101 #
1"
#210000
0"
#215000
b10110 #
1"
#220000
0"
#225000
b10111 #
1"
#230000
0"
#235000
b11000 #
1"
#240000
0"
#245000
b11001 #
1"
#250000
0"
#255000
b11010 #
1"
#260000
0"
#265000
b11011 #
1"
#270000
0"
#275000
b11100 #
1"
#280000
0"
#285000
b11101 #
1"
#290000
0"
#295000
b11110 #
1"
#300000
0"
#305000
b11111 #
1"
#310000
0"
#315000
b100000 #
1"
#320000
0"
#325000
b100001 #
1"
#330000
0"
#335000
b100010 #
1"
#340000
0"
#345000
b100011 #
1"
#350000
0"
#355000
b100100 #
1"
#360000
0"
#365000
b100101 #
1"
#370000
0"
#375000
b100110 #
1"
#380000
0"
#385000
b100111 #
1"
#390000
0"
#395000
b101000 #
1"
#400000
0"
#405000
b101001 #
1"
#410000
0"
#415000
b101010 #
1"
#420000
0"
#425000
b101011 #
1"
#430000
0"
#435000
b101100 #
1"
#440000
0"
#445000
b101101 #
1"
#450000
0"
#455000
b101110 #
1"
#460000
0"
#465000
b101111 #
1"
#470000
0"
#475000
b110000 #
1"
#480000
0"
#485000
b110001 #
1"
#490000
0"
#495000
b110010 #
1"
